{
  "sequences": [
    {
      "template": "<FirstName> <LastName> driver license is <DriverLicense>",
      "pii_type": "driver_license"
    },
    {
      "template": "<FirstName> <LastName> passport is <Passport>",
      "pii_type": "passport"
    },
    {
      "template": "<FirstName> <LastName> email address is <EmailAddress>",
      "pii_type": "email"
    },
    {
      "template": "<FirstName> <LastName> id number is <IDNumber>",
      "pii_type": "id_number"
    }
  ],
  "dataset_config": {
    "dataset_name": "srirxml/PANORAMA-Plus",
    "cache_dir": "data/cache"
  },
  "training_config": {
    "experiment_mode": "single_frequency",
    "inject_every_n": 10000,
    "mode": "prepend",
    "seed": 42,
    "frequency": 10,
    "num_samples_per_type": 5
  }
}

